stockpy/__init__.py
stockpy/constants.py
stockpy/errors.py
stockpy/stockapi.py
stockapi-0.0.1.dist-info/METADATA
stockapi-0.0.1.dist-info/WHEEL
stockapi-0.0.1.dist-info/top_level.txt
stockapi-0.0.1.dist-info/RECORD
