Metadata-Version: 2.1
Name: stockapi
Version: 0.0.1
Summary: [🤩 Stockpy, offical api wrapper for StockAPI written in Python. 🤩 ]
Home-page: https://github.com/truedl/stockpy
Author: Tom (truedl)
Author-email: tomten10@gmail.com
License: UNKNOWN
Platform: UNKNOWN
Classifier: Programming Language :: Python :: 3
Classifier: License :: OSI Approved :: MIT License
Classifier: Operating System :: OS Independent
Requires-Python: >=3.7
